moxel_http_driver/__init__.py
moxel_http_driver/driver.py
moxel_http_driver-0.0.1.post24.dist-info/DESCRIPTION.rst
moxel_http_driver-0.0.1.post24.dist-info/METADATA
moxel_http_driver-0.0.1.post24.dist-info/RECORD
moxel_http_driver-0.0.1.post24.dist-info/WHEEL
moxel_http_driver-0.0.1.post24.dist-info/entry_points.txt
moxel_http_driver-0.0.1.post24.dist-info/metadata.json
moxel_http_driver-0.0.1.post24.dist-info/top_level.txt
