Metadata-Version: 2.0
Name: moxel-http-driver
Version: 0.0.1.post24
Summary: generic http driver for moxel models
Home-page: http://moxel.ai
Author: moxel
Author-email: support@moxel.ai
License: MIT
Platform: UNKNOWN
